python_perl_storable/__init__.py
python_perl_storable/constants.py
python_perl_storable/exception.py
python_perl_storable/freeze.py
python_perl_storable/perl.py
python_perl_storable/thaw.py
python_perl_storable-0.1.0.data/scripts/pypls
python_perl_storable-0.1.0.dist-info/LICENSE
python_perl_storable-0.1.0.dist-info/METADATA
python_perl_storable-0.1.0.dist-info/WHEEL
python_perl_storable-0.1.0.dist-info/top_level.txt
python_perl_storable-0.1.0.dist-info/RECORD
