Metadata-Version: 2.1
Name: python-perl-storable
Version: 0.1.0
Summary: python_perl_storable - распаковывает структуру из формата perl-storable
Home-page: https://github.com/darviarush/python-perl-storable
Author: Yaroslav O. Kosmina
Author-email: darviarush@mail.ru
License: MIT
Platform: any
Classifier: Development Status :: 4 - Beta
Classifier: Topic :: Text Processing
Classifier: License :: OSI Approved :: MIT License
Classifier: Operating System :: OS Independent
Classifier: Programming Language :: Python :: 3
Classifier: Programming Language :: Python :: 3.3
Classifier: Programming Language :: Python :: 3.4
Classifier: Programming Language :: Python :: 3.5
Classifier: Programming Language :: Python :: 3.6
Classifier: Programming Language :: Python :: 3.7
Requires-Python: >=3.6
Requires-Dist: data-printer
Requires-Dist: argparse
